Workbook

Sheet 總覽
A1: 📊 個人財務總覽
A2: 計價幣別：新台幣（TWD） 資產更新時間：2026-05-07 20:23:08
A4: ── 資產分類明細 ──
B5: 💰 現金帳戶 | E5: ='現金帳戶'!E15 -> 18194500
B6: 📈 投資組合 | E6: ='投資'!H33 -> 1431961.2
B7: 🏠 固定資產 | E7: ='固定資產'!E8 -> 500000
B8: 📥 應收款 | E8: ='應收款'!E8 -> 5000000
B9: 💳 負債 | E9: ='負債'!E11 -> 3000000
B11: 📊 總資產 | E11: ='現金帳戶'!E15+'投資'!H33+'固定資產'!E8+'應收款'!E8 -> 25126461
B12: ✅ 淨資產 | E12: ='現金帳戶'!E15+'投資'!H33+'固定資產'!E8+'應收款'!E8-'負債'!E11 -> 22126461
I14: 現金帳戶 | J14: ='現金帳戶'!E15 -> 18194500
I15: 投資組合 | J15: ='投資'!H33 -> 1431961.2
I16: 固定資產 | J16: ='固定資產'!E8 -> 500000
I17: 應收款 | J17: ='應收款'!E8 -> 5000000
A19: 🎨 顏色規範：藍色文字 = 人工輸入值 黑色文字 = 公式計算 綠色文字 = 跨工作表參照

Sheet 設定
A1: ⚙️ 系統設定 — 匯率
A3: 貨幣名稱 | B3: 代號 | C3: 1外幣 = N 台幣 | D3: 資產更新時間
A4: 美元 | B4: USD | C4: 31.389 | D4: 46149.849
A5: 日圓 | B5: JPY | C5: 0.2007515 | D5: 46149.849
A6: 歐元 | B6: EUR | C6: 36.94736 | D6: 46149.849
A7: 港幣 | B7: HKD | C7: 4.007881 | D7: 46149.849
D8: 上次更新: 2026-05-07
A9: 📌 說明：藍色欄位為輸入欄。請定期更新匯率，所有工作表換算均參照此處。 顏色規範：藍色=人工輸入 黑色=公式計算 綠色=跨工作表參照

Sheet 現金帳戶
A1: 💰 現金帳戶
A2: 帳戶名稱 | B2: 幣別 | C2: 金額（原幣） | D2: 匯率（→台幣） | E2: 台幣金額 | F2: 最後操作時間 | G2: 資產更新時間
A3: 台新日幣 | B3: JPY | C3: 0 | D3: ='設定'!C5 -> 0.2007515 | E3: =IF(C3="","-",C3*D3) -> 0 | F3: 2026-04-18 00:00 | G3: 46149.849
A4: 台新台幣 | B4: TWD | C4: 500000 | D4: 1 | E4: =IF(C4="","-",C4*D4) -> 500000 | F4: 2026-04-18 00:00 | G4: 46149.849
A5: 永豐台幣 | B5: TWD | C5: 500000 | D5: 1 | E5: =IF(C5="","-",C5*D5) -> 500000 | F5: 2026-04-18 00:00 | G5: 46149.849
A6: 新光 | B6: TWD | C6: 500000 | D6: 1 | E6: =IF(C6="","-",C6*D6) -> 500000 | F6: 2026-02-07 00:00 | G6: 46149.849
A7: 中信台幣 | B7: TWD | C7: 500000 | D7: 1 | E7: =IF(C7="","-",C7*D7) -> 500000 | F7: 2026-04-18 00:00 | G7: 46149.849
A8: 美債 | B8: USD | C8: 0 | D8: ='設定'!C4 -> 31.389 | E8: =IF(C8="","-",C8*D8) -> 0 | F8: 2026-04-18 00:00 | G8: 46149.849
A9: 富邦台幣 | B9: TWD | C9: 500000 | D9: 1 | E9: =IF(C9="","-",C9*D9) -> 500000 | F9: 2026-04-20 00:00 | G9: 46149.849
A10: 富邦美金 | B10: USD | C10: 500000 | D10: ='設定'!C4 -> 31.389 | E10: =IF(C10="","-",C10*D10) -> 15694500 | F10: 2026-04-18 00:00 | G10: 46149.849
A11: 台新美金 | B11: USD | C11: 0 | D11: ='設定'!C4 -> 31.389 | E11: =IF(C11="","-",C11*D11) -> 0 | F11: 2026-04-18 00:00 | G11: 46149.849
B12: TWD | D12: 1 | E12: =IF(C12="","-",C12*D12) -> -
B13: TWD | D13: 1 | E13: =IF(C13="","-",C13*D13) -> -
B14: USD | D14: ='設定'!C4 -> 31.389 | E14: =IF(C14="","-",C14*D14) -> -
A15: 💰 現金帳戶合計 | E15: =SUM(E3:E14) -> 18194500 | G15: 46149.849

Sheet 投資
A1: 📈 投資組合
A2: 類別 | B2: 資產名稱 | C2: 代號 | D2: 持有數量 | E2: 幣別 | F2: 現價 | G2: 市值（原幣） | H2: 市值（台幣） | I2: 成本（台幣） | J2: 損益（台幣） | K2: 最後操作時間 | L2: 資產更新時間
A3: 美股ETF | B3: 信息科技指數ETF-Vanguard | C3: VGT | D3: 21 | E3: USD | F3: 109.56 | G3: =IF(OR(D3="",F3=""),"-",D3*F3) -> 2300.76 | H3: =IF(G3="-","-",IF(E3="TWD",G3,IF(E3="USD",G3*'設定'!C4,IF(E3="JPY",G3*'設定'!C5,IF(E3="EUR",G3*'設定'!C6,IF(E3="HKD",G3*'設定'!C7,G3)))))) -> 72218.556 | J3: =IF(OR(H3="-",I3=""),"-",H3-I3) -> - | L3: 46149.849
A4: 美股ETF | B4: 納斯達克100ETF-Invesco | C4: QQQ | D4: 20 | E4: USD | F4: 695.75 | G4: =IF(OR(D4="",F4=""),"-",D4*F4) -> 13915 | H4: =IF(G4="-","-",IF(E4="TWD",G4,IF(E4="USD",G4*'設定'!C4,IF(E4="JPY",G4*'設定'!C5,IF(E4="EUR",G4*'設定'!C6,IF(E4="HKD",G4*'設定'!C7,G4)))))) -> 436777.93 | J4: =IF(OR(H4="-",I4=""),"-",H4-I4) -> - | L4: 46149.849
A5: 美股ETF | B5: 全市場指數ETF-Vanguard | C5: VTI | D5: 20 | E5: USD | F5: 361.86 | G5: =IF(OR(D5="",F5=""),"-",D5*F5) -> 7237.2 | H5: =IF(G5="-","-",IF(E5="TWD",G5,IF(E5="USD",G5*'設定'!C4,IF(E5="JPY",G5*'設定'!C5,IF(E5="EUR",G5*'設定'!C6,IF(E5="HKD",G5*'設定'!C7,G5)))))) -> 227168.47 | J5: =IF(OR(H5="-",I5=""),"-",H5-I5) -> - | L5: 46149.849
A6: 美股ETF | B6: 標普500ETF-SPDR | C6: SPY | D6: 5 | E6: USD | F6: 733.83 | G6: =IF(OR(D6="",F6=""),"-",D6*F6) -> 3669.15 | H6: =IF(G6="-","-",IF(E6="TWD",G6,IF(E6="USD",G6*'設定'!C4,IF(E6="JPY",G6*'設定'!C5,IF(E6="EUR",G6*'設定'!C6,IF(E6="HKD",G6*'設定'!C7,G6)))))) -> 115170.95 | J6: =IF(OR(H6="-",I6=""),"-",H6-I6) -> - | L6: 46149.849
A7: 美股ETF | B7: 標普500ETF-Vanguard | C7: VOO | D7: 5 | E7: USD | F7: 674.66 | G7: =IF(OR(D7="",F7=""),"-",D7*F7) -> 3373.3 | H7: =IF(G7="-","-",IF(E7="TWD",G7,IF(E7="USD",G7*'設定'!C4,IF(E7="JPY",G7*'設定'!C5,IF(E7="EUR",G7*'設定'!C6,IF(E7="HKD",G7*'設定'!C7,G7)))))) -> 105884.51 | J7: =IF(OR(H7="-",I7=""),"-",H7-I7) -> - | L7: 46149.849
A8: 美股ETF | B8: Alpha Architect 1-3 Month Box E | C8: BOXX | E8: USD | F8: 116.59 | G8: =IF(OR(D8="",F8=""),"-",D8*F8) -> - | H8: =IF(G8="-","-",IF(E8="TWD",G8,IF(E8="USD",G8*'設定'!C4,IF(E8="JPY",G8*'設定'!C5,IF(E8="EUR",G8*'設定'!C6,IF(E8="HKD",G8*'設定'!C7,G8)))))) -> - | J8: =IF(OR(H8="-",I8=""),"-",H8-I8) -> - | L8: 46149.849
A9: 美股 | B9: 谷歌-C | C9: GOOGL | D9: 5 | E9: USD | F9: 397.82 | G9: =IF(OR(D9="",F9=""),"-",D9*F9) -> 1989.1 | H9: =IF(G9="-","-",IF(E9="TWD",G9,IF(E9="USD",G9*'設定'!C4,IF(E9="JPY",G9*'設定'!C5,IF(E9="EUR",G9*'設定'!C6,IF(E9="HKD",G9*'設定'!C7,G9)))))) -> 62435.86 | J9: =IF(OR(H9="-",I9=""),"-",H9-I9) -> - | L9: 46149.849
A10: 美股 | B10: Meta Platforms Inc-A | C10: META | D10: 5 | E10: USD | F10: 612.88 | G10: =IF(OR(D10="",F10=""),"-",D10*F10) -> 3064.4 | H10: =IF(G10="-","-",IF(E10="TWD",G10,IF(E10="USD",G10*'設定'!C4,IF(E10="JPY",G10*'設定'!C5,IF(E10="EUR",G10*'設定'!C6,IF(E10="HKD",G10*'設定'!C7,G10)))))) -> 96188.452 | J10: =IF(OR(H10="-",I10=""),"-",H10-I10) -> - | L10: 46149.849
A11: 美股 | B11: 微軟 | C11: MSFT | D11: 5 | E11: USD | F11: 413.87 | G11: =IF(OR(D11="",F11=""),"-",D11*F11) -> 2069.35 | H11: =IF(G11="-","-",IF(E11="TWD",G11,IF(E11="USD",G11*'設定'!C4,IF(E11="JPY",G11*'設定'!C5,IF(E11="EUR",G11*'設定'!C6,IF(E11="HKD",G11*'設定'!C7,G11)))))) -> 64954.827 | J11: =IF(OR(H11="-",I11=""),"-",H11-I11) -> - | L11: 46149.849
A12: 美股 | B12: 超威半導體 | C12: AMD | D12: 5 | E12: USD | F12: 421.47 | G12: =IF(OR(D12="",F12=""),"-",D12*F12) -> 2107.35 | H12: =IF(G12="-","-",IF(E12="TWD",G12,IF(E12="USD",G12*'設定'!C4,IF(E12="JPY",G12*'設定'!C5,IF(E12="EUR",G12*'設定'!C6,IF(E12="HKD",G12*'設定'!C7,G12)))))) -> 66147.609 | J12: =IF(OR(H12="-",I12=""),"-",H12-I12) -> - | L12: 46149.849
A13: 美股 | B13: 英偉達 | C13: NVDA | D13: 5 | E13: USD | F13: 207.67 | G13: =IF(OR(D13="",F13=""),"-",D13*F13) -> 1038.35 | H13: =IF(G13="-","-",IF(E13="TWD",G13,IF(E13="USD",G13*'設定'!C4,IF(E13="JPY",G13*'設定'!C5,IF(E13="EUR",G13*'設定'!C6,IF(E13="HKD",G13*'設定'!C7,G13)))))) -> 32592.768 | J13: =IF(OR(H13="-",I13=""),"-",H13-I13) -> - | L13: 46149.849
A14: 美股 | B14: 伯克希爾哈撒韋-B | C14: BRK.B | D14: 5 | E14: USD | F14: 469.83 | G14: =IF(OR(D14="",F14=""),"-",D14*F14) -> 2349.15 | H14: =IF(G14="-","-",IF(E14="TWD",G14,IF(E14="USD",G14*'設定'!C4,IF(E14="JPY",G14*'設定'!C5,IF(E14="EUR",G14*'設定'!C6,IF(E14="HKD",G14*'設定'!C7,G14)))))) -> 73737.469 | J14: =IF(OR(H14="-",I14=""),"-",H14-I14) -> - | L14: 46149.849
A15: 美股 | B15: 蘋果 | C15: AAPL | D15: 5 | E15: USD | F15: 287.51 | G15: =IF(OR(D15="",F15=""),"-",D15*F15) -> 1437.55 | H15: =IF(G15="-","-",IF(E15="TWD",G15,IF(E15="USD",G15*'設定'!C4,IF(E15="JPY",G15*'設定'!C5,IF(E15="EUR",G15*'設定'!C6,IF(E15="HKD",G15*'設定'!C7,G15)))))) -> 45123.257 | J15: =IF(OR(H15="-",I15=""),"-",H15-I15) -> - | L15: 46149.849
A16: 台股 | B16: 廣達 | C16: 2382 | D16: 5 | E16: TWD | F16: 344 | G16: =IF(OR(D16="",F16=""),"-",D16*F16) -> 1720 | H16: =IF(G16="-","-",IF(E16="TWD",G16,IF(E16="USD",G16*'設定'!C4,IF(E16="JPY",G16*'設定'!C5,IF(E16="EUR",G16*'設定'!C6,IF(E16="HKD",G16*'設定'!C7,G16)))))) -> 1720 | J16: =IF(OR(H16="-",I16=""),"-",H16-I16) -> - | L16: 46149.849
A17: 台股 | B17: 鴻海 | C17: 2317 | D17: 5 | E17: TWD | F17: 253.5 | G17: =IF(OR(D17="",F17=""),"-",D17*F17) -> 1267.5 | H17: =IF(G17="-","-",IF(E17="TWD",G17,IF(E17="USD",G17*'設定'!C4,IF(E17="JPY",G17*'設定'!C5,IF(E17="EUR",G17*'設定'!C6,IF(E17="HKD",G17*'設定'!C7,G17)))))) -> 1267.5 | J17: =IF(OR(H17="-",I17=""),"-",H17-I17) -> - | L17: 46149.849
A18: 台股 | B18: 聯發科 | C18: 2454 | D18: 5 | E18: TWD | F18: 3420 | G18: =IF(OR(D18="",F18=""),"-",D18*F18) -> 17100 | H18: =IF(G18="-","-",IF(E18="TWD",G18,IF(E18="USD",G18*'設定'!C4,IF(E18="JPY",G18*'設定'!C5,IF(E18="EUR",G18*'設定'!C6,IF(E18="HKD",G18*'設定'!C7,G18)))))) -> 17100 | J18: =IF(OR(H18="-",I18=""),"-",H18-I18) -> - | L18: 46149.849
A19: 台股 | B19: 台積電 | C19: 2330 | D19: 5 | E19: TWD | F19: 2310 | G19: =IF(OR(D19="",F19=""),"-",D19*F19) -> 11550 | H19: =IF(G19="-","-",IF(E19="TWD",G19,IF(E19="USD",G19*'設定'!C4,IF(E19="JPY",G19*'設定'!C5,IF(E19="EUR",G19*'設定'!C6,IF(E19="HKD",G19*'設定'!C7,G19)))))) -> 11550 | J19: =IF(OR(H19="-",I19=""),"-",H19-I19) -> - | K19: 2026-04-17 00:00 | L19: 46149.849
A20: 台灣ETF | B20: 元大台灣50 | C20: 0050 | D20: 5 | E20: TWD | F20: 97.7 | G20: =IF(OR(D20="",F20=""),"-",D20*F20) -> 488.5 | H20: =IF(G20="-","-",IF(E20="TWD",G20,IF(E20="USD",G20*'設定'!C4,IF(E20="JPY",G20*'設定'!C5,IF(E20="EUR",G20*'設定'!C6,IF(E20="HKD",G20*'設定'!C7,G20)))))) -> 488.5 | J20: =IF(OR(H20="-",I20=""),"-",H20-I20) -> - | L20: 46149.849
A21: 台灣ETF | B21: 元大美債20年 | C21: 00679B | D21: 5 | E21: TWD | F21: 27.04 | G21: =IF(OR(D21="",F21=""),"-",D21*F21) -> 135.2 | H21: =IF(G21="-","-",IF(E21="TWD",G21,IF(E21="USD",G21*'設定'!C4,IF(E21="JPY",G21*'設定'!C5,IF(E21="EUR",G21*'設定'!C6,IF(E21="HKD",G21*'設定'!C7,G21)))))) -> 135.2 | J21: =IF(OR(H21="-",I21=""),"-",H21-I21) -> - | L21: 46132.999
A22: 台灣ETF | B22: 元大台灣50正2 | C22: 00631L | D22: 5 | E22: TWD | F22: 33.06 | G22: =IF(OR(D22="",F22=""),"-",D22*F22) -> 165.3 | H22: =IF(G22="-","-",IF(E22="TWD",G22,IF(E22="USD",G22*'設定'!C4,IF(E22="JPY",G22*'設定'!C5,IF(E22="EUR",G22*'設定'!C6,IF(E22="HKD",G22*'設定'!C7,G22)))))) -> 165.3 | J22: =IF(OR(H22="-",I22=""),"-",H22-I22) -> - | L22: 46149.849
A23: 台灣ETF | B23: 富邦台50 | C23: 006208 | D23: 5 | E23: TWD | F23: 226.8 | G23: =IF(OR(D23="",F23=""),"-",D23*F23) -> 1134 | H23: =IF(G23="-","-",IF(E23="TWD",G23,IF(E23="USD",G23*'設定'!C4,IF(E23="JPY",G23*'設定'!C5,IF(E23="EUR",G23*'設定'!C6,IF(E23="HKD",G23*'設定'!C7,G23)))))) -> 1134 | J23: =IF(OR(H23="-",I23=""),"-",H23-I23) -> - | L23: 46149.849
A33: 📈 投資組合合計 | H33: =SUMIF(H3:H25,"<>-") -> 1431961.2 | I33: =SUMIF(I3:I25,"<>0") -> 0 | J33: =SUMIF(J3:J25,"<>-") -> 0
A34: 📌 更新說明：「現價」欄位（藍色）請定期手動輸入最新市場價格。幣別請填 USD / TWD / JPY 等。成本以台幣填寫。損益 = 市值(台幣) - 成本(台幣)。

Sheet 固定資產
A1: 🏠 固定資產
A2: 資產名稱 | B2: 描述 | C2: 幣別 | D2: 金額（原幣） | E2: 台幣金額 | F2: 最後操作時間
A3: 不動產 | B3: 房產（估值） | C3: TWD | D3: 500000 | E3: =IF(D3="","-",IF(C3="TWD",D3,IF(C3="USD",D3*'設定'!C4,IF(C3="JPY",D3*'設定'!C5,IF(C3="EUR",D3*'設定'!C6,IF(C3="HKD",D3*'設定'!C7,D3)))))) -> 500000
C4: TWD | E4: =IF(D4="","-",IF(C4="TWD",D4,IF(C4="USD",D4*'設定'!C4,IF(C4="JPY",D4*'設定'!C5,IF(C4="EUR",D4*'設定'!C6,IF(C4="HKD",D4*'設定'!C7,D4)))))) -> -
C5: TWD | E5: =IF(D5="","-",IF(C5="TWD",D5,IF(C5="USD",D5*'設定'!C4,IF(C5="JPY",D5*'設定'!C5,IF(C5="EUR",D5*'設定'!C6,IF(C5="HKD",D5*'設定'!C7,D5)))))) -> -
C6: USD | E6: =IF(D6="","-",IF(C6="TWD",D6,IF(C6="USD",D6*'設定'!C4,IF(C6="JPY",D6*'設定'!C5,IF(C6="EUR",D6*'設定'!C6,IF(C6="HKD",D6*'設定'!C7,D6)))))) -> -
C7: TWD | E7: =IF(D7="","-",IF(C7="TWD",D7,IF(C7="USD",D7*'設定'!C4,IF(C7="JPY",D7*'設定'!C5,IF(C7="EUR",D7*'設定'!C6,IF(C7="HKD",D7*'設定'!C7,D7)))))) -> -
A8: 🏠 固定資產合計 | E8: =SUMIF(E3:E7,"<>-") -> 500000

Sheet 負債
A1: 💳 負債
A2: 項目 | B2: 描述 | C2: 幣別 | D2: 金額（原幣） | E2: 台幣金額 | F2: 最後操作時間
A3: 增貸 | B3: 新建帳戶 | C3: TWD | D3: 500000 | E3: =IF(D3="","-",IF(C3="TWD",D3,IF(C3="USD",D3*'設定'!C4,IF(C3="JPY",D3*'設定'!C5,IF(C3="EUR",D3*'設定'!C6,IF(C3="HKD",D3*'設定'!C7,D3)))))) -> 500000
A4: 項目1 | B4: 修改餘額 | C4: TWD | D4: 500000 | E4: =IF(D4="","-",IF(C4="TWD",D4,IF(C4="USD",D4*'設定'!C4,IF(C4="JPY",D4*'設定'!C5,IF(C4="EUR",D4*'設定'!C6,IF(C4="HKD",D4*'設定'!C7,D4)))))) -> 500000
A5: 項目2 | B5: 新建帳戶 | C5: TWD | D5: 500000 | E5: =IF(D5="","-",IF(C5="TWD",D5,IF(C5="USD",D5*'設定'!C4,IF(C5="JPY",D5*'設定'!C5,IF(C5="EUR",D5*'設定'!C6,IF(C5="HKD",D5*'設定'!C7,D5)))))) -> 500000
A6: 項目3 | B6: 修改餘額 | C6: TWD | D6: 500000 | E6: =IF(D6="","-",IF(C6="TWD",D6,IF(C6="USD",D6*'設定'!C4,IF(C6="JPY",D6*'設定'!C5,IF(C6="EUR",D6*'設定'!C6,IF(C6="HKD",D6*'設定'!C7,D6)))))) -> 500000
A7: 項目4 | B7: 修改餘額 | C7: TWD | D7: 500000 | E7: =IF(D7="","-",IF(C7="TWD",D7,IF(C7="USD",D7*'設定'!C4,IF(C7="JPY",D7*'設定'!C5,IF(C7="EUR",D7*'設定'!C6,IF(C7="HKD",D7*'設定'!C7,D7)))))) -> 500000
A8: 房貸 | B8: 修改餘額 | C8: TWD | D8: 500000 | E8: =IF(D8="","-",IF(C8="TWD",D8,IF(C8="USD",D8*'設定'!C4,IF(C8="JPY",D8*'設定'!C5,IF(C8="EUR",D8*'設定'!C6,IF(C8="HKD",D8*'設定'!C7,D8)))))) -> 500000
C9: TWD | E9: =IF(D9="","-",IF(C9="TWD",D9,IF(C9="USD",D9*'設定'!C4,IF(C9="JPY",D9*'設定'!C5,IF(C9="EUR",D9*'設定'!C6,IF(C9="HKD",D9*'設定'!C7,D9)))))) -> -
C10: TWD | E10: =IF(D10="","-",IF(C10="TWD",D10,IF(C10="USD",D10*'設定'!C4,IF(C10="JPY",D10*'設定'!C5,IF(C10="EUR",D10*'設定'!C6,IF(C10="HKD",D10*'設定'!C7,D10)))))) -> -
A11: 💳 負債合計 | E11: =SUMIF(E3:E10,"<>-") -> 3000000

Sheet 應收款
A1: 📥 應收款
A2: 項目 | B2: 描述 | C2: 幣別 | D2: 金額（原幣） | E2: 台幣金額 | F2: 最後操作時間
A3: 某人 | B3: 修改餘額 | C3: TWD | D3: 5000000 | E3: =IF(D3="","-",IF(C3="TWD",D3,IF(C3="USD",D3*'設定'!C4,IF(C3="JPY",D3*'設定'!C5,IF(C3="EUR",D3*'設定'!C6,IF(C3="HKD",D3*'設定'!C7,D3)))))) -> 5000000
C4: TWD | E4: =IF(D4="","-",IF(C4="TWD",D4,IF(C4="USD",D4*'設定'!C4,IF(C4="JPY",D4*'設定'!C5,IF(C4="EUR",D4*'設定'!C6,IF(C4="HKD",D4*'設定'!C7,D4)))))) -> -
C5: USD | E5: =IF(D5="","-",IF(C5="TWD",D5,IF(C5="USD",D5*'設定'!C4,IF(C5="JPY",D5*'設定'!C5,IF(C5="EUR",D5*'設定'!C6,IF(C5="HKD",D5*'設定'!C7,D5)))))) -> -
C6: TWD | E6: =IF(D6="","-",IF(C6="TWD",D6,IF(C6="USD",D6*'設定'!C4,IF(C6="JPY",D6*'設定'!C5,IF(C6="EUR",D6*'設定'!C6,IF(C6="HKD",D6*'設定'!C7,D6)))))) -> -
C7: TWD | E7: =IF(D7="","-",IF(C7="TWD",D7,IF(C7="USD",D7*'設定'!C4,IF(C7="JPY",D7*'設定'!C5,IF(C7="EUR",D7*'設定'!C6,IF(C7="HKD",D7*'設定'!C7,D7)))))) -> -
A8: 📥 應收款合計 | E8: =SUMIF(E3:E7,"<>-") -> 5000000

Sheet 歷史紀錄
A1: 📊 每日資產快照 — 歷史紀錄
A2: 日期 | B2: 總資產 | C2: 淨資產 | D2: 現金 | E2: 投資 | F2: 固定資產 | G2: 負債 | H2: 應收款
A33: 📌 每日更新：請在新的一行輸入日期，並從「總覽」頁複製貼上（選擇性貼上→數值）各項合計。
